usermapper/__init__.py
usermapper/__main__.py
usermapper/mapperdata.py
usermapper/usermapper.py
usermapper-0.3.dist-info/LICENSE
usermapper-0.3.dist-info/METADATA
usermapper-0.3.dist-info/WHEEL
usermapper-0.3.dist-info/entry_points.txt
usermapper-0.3.dist-info/top_level.txt
usermapper-0.3.dist-info/RECORD
