Metadata-Version: 2.1
Name: usermapper
Version: 0.3
Summary: Create a manual authentication file for the Guacamole remote access gateway from a simple configuration file.
Author-email: Brian Linkletter <mail@brianlinkletter.ca>
License: GPLv3
Project-URL: Repository, https://github.com/blinklet/usermapper
Project-URL: Blog, https://learningwithcode.com
Keywords: Guacamole,YAML,XML,authentication
Classifier: Framework :: Flask
Classifier: Programming Language :: Python :: 3
Requires-Python: >=3.7
License-File: LICENSE
Requires-Dist: PyYAML
